latexcornouaille/__init__.py
latexcornouaille/cli.py
latexcornouaille/latexcornouaille.py
latexcornouaille-0.1.4.dist-info/entry_points.txt
latexcornouaille-0.1.4.dist-info/LICENSE
latexcornouaille-0.1.4.dist-info/WHEEL
latexcornouaille-0.1.4.dist-info/METADATA
latexcornouaille-0.1.4.dist-info/RECORD
